nonebot_plugin_maimai-0.5.3.dist-info/METADATA
nonebot_plugin_maimai-0.5.3.dist-info/WHEEL
nonebot_plugin_maimai-0.5.3.dist-info/entry_points.txt
nonebot_plugin_maimai-0.5.3.dist-info/licenses/LICENSE
nonebot_plugin_maimai/__init__.py
nonebot_plugin_maimai/__main__.py
nonebot_plugin_maimai/api.py
nonebot_plugin_maimai/libraries/__init__.py
nonebot_plugin_maimai/libraries/image.py
nonebot_plugin_maimai/libraries/maimai_best_40.py
nonebot_plugin_maimai/libraries/maimai_best_50.py
nonebot_plugin_maimai/libraries/maimaidx_music.py
nonebot_plugin_maimai/libraries/tool.py
nonebot_plugin_maimai/public.py
nonebot_plugin_maimai-0.5.3.dist-info/RECORD
