Metadata-Version: 2.1
Name: nonebot_plugin_maimai
Version: 0.5.3
Summary: Maimai DX plugin for NoneBot
Keywords: maimai,nonebot2,plugin
Author-Email: Agnes_Digital <Z735803792@163.com>
License: MIT
Classifier: License :: OSI Approved :: MIT License
Classifier: Programming Language :: Python
Classifier: Programming Language :: Python :: 3
Classifier: Programming Language :: Python :: 3.9
Classifier: Programming Language :: Python :: 3.10
Classifier: Programming Language :: Python :: 3.11
Classifier: Programming Language :: Python :: 3.12
Classifier: Operating System :: OS Independent
Project-URL: homepage, https://github.com/Agnes4m/maimai_plugin/tree/nonebot2.0.0
Requires-Python: <4.0,>=3.9
Requires-Dist: aiohttp>=3.8.3
Requires-Dist: nonebot2>=2.1.0
Requires-Dist: nonebot2[fastapi]>=2.3.3
Requires-Dist: nonebot-adapter-onebot>=2.1.3
Requires-Dist: pillow>10.0.0
Requires-Dist: httpx>=0.22.0
Requires-Dist: nonebot_plugin_alconna>=0.3.2
Requires-Dist: aiofiles>=24.1.0
